alterootheme
