Metadata-Version: 1.0
Name: alterootheme.busycity
Version: 1.0a6
Summary: Free City Plone 3.0 Theme
Home-page: http://themes.alteroo.com
Author: David Bain
Author-email: david.bain@alteroo.com
License: GPL
Keywords: web zope plone theme
Platform: UNKNOWN
Classifier: Framework :: Plone
Classifier: Framework :: Zope2
Classifier: Framework :: Zope3
Classifier: Programming Language :: Python
Classifier: Topic :: Software Development :: Libraries :: Python Modules
